pulumi_opsgenie/__init__.py
pulumi_opsgenie/_inputs.py
pulumi_opsgenie/_utilities.py
pulumi_opsgenie/alert_policy.py
pulumi_opsgenie/api_integration.py
pulumi_opsgenie/custom_role.py
pulumi_opsgenie/email_integration.py
pulumi_opsgenie/escalation.py
pulumi_opsgenie/get_escalation.py
pulumi_opsgenie/get_heartbeat.py
pulumi_opsgenie/get_schedule.py
pulumi_opsgenie/get_service.py
pulumi_opsgenie/get_team.py
pulumi_opsgenie/get_user.py
pulumi_opsgenie/heartbeat.py
pulumi_opsgenie/incident_template.py
pulumi_opsgenie/integration_action.py
pulumi_opsgenie/maintenance.py
pulumi_opsgenie/notification_policy.py
pulumi_opsgenie/notification_rule.py
pulumi_opsgenie/outputs.py
pulumi_opsgenie/provider.py
pulumi_opsgenie/pulumi-plugin.json
pulumi_opsgenie/py.typed
pulumi_opsgenie/schedule.py
pulumi_opsgenie/schedule_rotation.py
pulumi_opsgenie/service.py
pulumi_opsgenie/service_incident_rule.py
pulumi_opsgenie/team.py
pulumi_opsgenie/team_routing_rule.py
pulumi_opsgenie/user.py
pulumi_opsgenie/user_contact.py
pulumi_opsgenie/config/__init__.py
pulumi_opsgenie/config/__init__.pyi
pulumi_opsgenie/config/vars.py
pulumi_opsgenie-1.3.19.dist-info/METADATA
pulumi_opsgenie-1.3.19.dist-info/WHEEL
pulumi_opsgenie-1.3.19.dist-info/top_level.txt
pulumi_opsgenie-1.3.19.dist-info/RECORD
